[
 {
  "application_id": "ca6ed33d-05a9-447d-b42c-64cb3c93e17c",
  "name": "Vim",
  "name_e": "",
  "name_r": "",
  "description": "Vim ist ein freier Texteditor für die Arbeit mit einer Vi-kompatiblen Befehlszeilenschnittstelle.",
  "description_e": "",
  "description_r": "",
  "thumbnail": "assets/icons/vim.svg",
  "image": "",
  "url": "https://www.vim.org/",
  "alternatename": "Vi IMproved",
  "alternatename_e": "",
  "alternatename_r": "",
  "keywords": "Vim, Texteditor, Vi, Befehlszeile",
  "keywords_e": "",
  "keywords_r": "",
  "version": "8.2.3401",
  "applicationtype_id": "f08cca44-ca0f-4c50-ab5d-f58731cd5b0b"
 },
 {
  "application_id": "8d2f99d0-528f-48a7-8744-1e557e16204c",
  "name": "GIMP",
  "name_e": "",
  "name_r": "",
  "description": "GIMP ist ein kostenloses, plattformübergreifendes Bildbearbeitungsprogramm für die Erstellung und Bearbeitung von digitalen Bildern.",
  "description_e": "",
  "description_r": "",
  "thumbnail": "assets/icons/gimp.svg",
  "image": "",
  "url": "https://www.gimp.org/",
  "alternatename": "GNU Image Manipulation Program",
  "alternatename_e": "",
  "alternatename_r": "",
  "keywords": "GIMP, Bildbearbeitung, Photoshop-Alternative",
  "keywords_e": "",
  "keywords_r": "",
  "version": "2.10.28",
  "applicationtype_id": "f08cca44-ca0f-4c50-ab5d-f58731cd5b0b"
 },
 {
  "application_id": "dac43efa-79b4-4203-92cb-938c38bcdafc",
  "name": "Adobe Photoshop",
  "name_e": "",
  "name_r": "",
  "description": "Adobe Photoshop ist ein professionelles Bildbearbeitungsprogramm für Kreative.",
  "description_e": "",
  "description_r": "",
  "thumbnail": "assets/icons/photoshop.svg",
  "image": "",
  "url": "https://www.adobe.com/products/photoshop.html",
  "alternatename": "Photoshop, Adobe Creative Suite",
  "alternatename_e": "",
  "alternatename_r": "",
  "keywords": "Bildbearbeitung, Grafikdesign, Kreativität, Adobe Creative Cloud",
  "keywords_e": "",
  "keywords_r": "",
  "version": "2022",
  "applicationtype_id": "f08cca44-ca0f-4c50-ab5d-f58731cd5b0b"
 },
 {
  "application_id": "81d8ed40-8f7d-4f92-b3f6-77c49bb96937",
  "name": "Inkscape",
  "name_e": "",
  "name_r": "",
  "description": "Inkscape ist ein professionelles Vektorgrafikprogramm, das eine kostenlose und Open-Source-Alternative zu Adobe Illustrator bietet.",
  "description_e": "",
  "description_r": "",
  "thumbnail": "assets/icons/inkscape.svg",
  "image": "",
  "url": "https://inkscape.org/",
  "alternatename": "Inkscape",
  "alternatename_e": "",
  "alternatename_r": "",
  "keywords": "Inkscape, Vektorgrafik, Open-Source, Adobe Illustrator",
  "keywords_e": "",
  "keywords_r": "",
  "version": "1.1",
  "applicationtype_id": "f08cca44-ca0f-4c50-ab5d-f58731cd5b0b"
 },
 {
  "application_id": "add9f4f3-4e4f-4132-98b3-28399f42f805",
  "name": "Unity",
  "name_e": "",
  "name_r": "",
  "description": "Unity ist eine plattformübergreifende Game Engine, die zur Entwicklung von Videospielen für PC, Konsolen, Mobilgeräte und Websites verwendet wird.",
  "description_e": "",
  "description_r": "",
  "thumbnail": "assets/icons/unity.svg",
  "image": "",
  "url": "https://unity.com/",
  "alternatename": "Unity3D",
  "alternatename_e": "",
  "alternatename_r": "",
  "keywords": "Unity, Unity3D, Game Engine, 3D Game Development",
  "keywords_e": "",
  "keywords_r": "",
  "version": "2020.3.19f1",
  "applicationtype_id": "f08cca44-ca0f-4c50-ab5d-f58731cd5b0b"
 },
 {
  "application_id": "650d6e4f-9f3e-46c9-b85c-a9544548ddca",
  "name": "Pygame",
  "name_e": "",
  "name_r": "",
  "description": "Pygame ist eine Sammlung von Python-Modulen, die für die Entwicklung von Videospielen entwickelt wurden.",
  "description_e": "",
  "description_r": "",
  "thumbnail": "assets/icons/pygame.webp",
  "image": "",
  "url": "https://www.pygame.org/",
  "alternatename": "Pygame-Bibliothek",
  "alternatename_e": "",
  "alternatename_r": "",
  "keywords": "Python, Pygame, Game Development, Game Programming, 2D-Spiele",
  "keywords_e": "",
  "keywords_r": "",
  "version": "2.0.1",
  "applicationtype_id": "b4d1e8ad-657e-4c32-8b9c-3ba8f59f74eb"
 },
 {
  "application_id": "78c1f716-b8e8-4ac6-8ea4-e40d04c5fe1e",
  "name": "Panda3D",
  "name_e": "",
  "name_r": "",
  "description": "Panda3D ist eine Game Engine, ein Framework für 3D-Rendering und Game Development für Python- und C++-Programme.",
  "description_e": "",
  "description_r": "",
  "thumbnail": "assets/icons/panda3d.webp",
  "image": "",
  "url": "https://www.panda3d.org/",
  "alternatename": "Panda3D-Engine",
  "alternatename_e": "",
  "alternatename_r": "",
  "keywords": "Python, Panda3D, Game Engine, Game Development, 3D-Spiele",
  "keywords_e": "",
  "keywords_r": "",
  "version": "1.10.11",
  "applicationtype_id": "b4d1e8ad-657e-4c32-8b9c-3ba8f59f74eb"
 },
 {
  "application_id": "3379cbf0-723b-4d4e-b307-70aaeab729f9",
  "name": "React",
  "name_e": "",
  "name_r": "",
  "description": "React ist eine JavaScript-Bibliothek zum Erstellen von Benutzeroberflächen.",
  "description_e": "",
  "description_r": "",
  "thumbnail": "assets/icons/react.svg",
  "image": "",
  "url": "https://reactjs.org/",
  "alternatename": "ReactJS",
  "alternatename_e": "",
  "alternatename_r": "",
  "keywords": "React, ReactJS, JavaScript-Bibliothek, Front-End-Entwicklung",
  "keywords_e": "",
  "keywords_r": "",
  "version": "17.0.2",
  "applicationtype_id": "b4d1e8ad-657e-4c32-8b9c-3ba8f59f74eb"
 },
 {
  "application_id": "ec1587fb-6d01-448b-aca2-07d5c913e700",
  "name": "Vue.js",
  "name_e": "",
  "name_r": "",
  "description": "Vue.js ist ein Open-Source-JavaScript-Framework zum Erstellen von Benutzeroberflächen und Single-Page-Anwendungen.",
  "description_e": "",
  "description_r": "",
  "thumbnail": "assets/icons/vue.svg",
  "image": "",
  "url": "https://vuejs.org/",
  "alternatename": "VueJS",
  "alternatename_e": "",
  "alternatename_r": "",
  "keywords": "Vue.js, VueJS, JavaScript-Framework, Front-End-Entwicklung",
  "keywords_e": "",
  "keywords_r": "",
  "version": "3.2.29",
  "applicationtype_id": "b4d1e8ad-657e-4c32-8b9c-3ba8f59f74eb"
 },
 {
  "application_id": "114ae290-cb93-43f0-adf6-52c4ee0661be",
  "name": "Selenium",
  "name_e": "",
  "name_r": "",
  "description": "Selenium ist eine Suite von Tools zum Automatisieren von Webbrowsern auf vielen Plattformen.",
  "description_e": "",
  "description_r": "",
  "thumbnail": "assets/icons/selenium.svg",
  "image": "",
  "url": "https://www.selenium.dev/",
  "alternatename": "Selenium WebDriver",
  "alternatename_e": "",
  "alternatename_r": "",
  "keywords": "Selenium, Selenium WebDriver, Automatisierte Tests, Webtests",
  "keywords_e": "",
  "keywords_r": "",
  "version": "4.1.0",
  "applicationtype_id": "b4d1e8ad-657e-4c32-8b9c-3ba8f59f74eb"
 },
 {
  "application_id": "04dcbb50-3f08-4a6c-8f7f-7c00d4f9bd07",
  "name": "Swing",
  "name_e": "",
  "name_r": "",
  "description": "Swing ist ein GUI-Widget-Toolkit für Java, das die Erstellung von Desktop-Anwendungen mit grafischer Benutzeroberfläche ermöglicht.",
  "description_e": "",
  "description_r": "",
  "thumbnail": "assets/icons/swing.webp",
  "image": "",
  "url": "https://docs.oracle.com/javase/tutorial/uiswing/",
  "alternatename": "Java Swing",
  "alternatename_e": "",
  "alternatename_r": "",
  "keywords": "Swing, Java, GUI, Bibliothek",
  "keywords_e": "",
  "keywords_r": "",
  "version": "Java 16",
  "applicationtype_id": "b4d1e8ad-657e-4c32-8b9c-3ba8f59f74eb"
 },
 {
  "application_id": "9cef1ae1-f01f-4d7f-a7ed-e2b82a8e7cb9",
  "name": "Ursina",
  "name_e": "",
  "name_r": "",
  "description": "Ursina ist eine Python-Bibliothek zur Entwicklung von 2D- und einfachen 3D-Spielen.",
  "description_e": "",
  "description_r": "",
  "thumbnail": "assets/icons/ursina.webp",
  "image": "",
  "url": "https://www.ursinaengine.org/",
  "alternatename": "Ursina-Engine",
  "alternatename_e": "",
  "alternatename_r": "",
  "keywords": "Python, Ursina, Game Engine, Game Development,",
  "keywords_e": "",
  "keywords_r": "",
  "version": "5.2.0",
  "applicationtype_id": "b4d1e8ad-657e-4c32-8b9c-3ba8f59f74eb"
 },
 {
  "application_id": "82e61456-4ab4-4823-824b-1d35b4750b00",
  "name": "GlassFish",
  "name_e": "",
  "name_r": "",
  "description": "GlassFish ist ein kostenloses und Open-Source-Application-Server für das Erstellen und Bereitstellen von Webanwendungen auf der Java-EE-Plattform.",
  "description_e": "",
  "description_r": "",
  "thumbnail": "assets/icons/glassfish.svg",
  "image": "",
  "url": "https://javaee.github.io/glassfish/",
  "alternatename": "GlassFish Server",
  "alternatename_e": "",
  "alternatename_r": "",
  "keywords": "GlassFish, Anwendungsserver, Java EE",
  "keywords_e": "",
  "keywords_r": "",
  "version": "5.1.0",
  "applicationtype_id": "d1a58af3-8d41-458d-bacb-6ef96ee3bd29"
 },
 {
  "application_id": "de327070-f7fd-42ce-84e1-19a9d06d2528",
  "name": "Tomcat7",
  "name_e": "",
  "name_r": "",
  "description": "Apache Tomcat 7 ist eine Open-Source-Softwareimplementierung der Java Servlet, JavaServer Pages, Java Expression Language und Java WebSocket-Technologien.",
  "description_e": "",
  "description_r": "",
  "thumbnail": "assets/icons/tomcat.webp",
  "image": "",
  "url": "http://tomcat.apache.org/tomcat-7.0-doc/",
  "alternatename": "Apache Tomcat 7",
  "alternatename_e": "",
  "alternatename_r": "",
  "keywords": "Tomcat, Anwendungsserver, Servlet-Container",
  "keywords_e": "",
  "keywords_r": "",
  "version": "7.0.107",
  "applicationtype_id": "d1a58af3-8d41-458d-bacb-6ef96ee3bd29"
 },
 {
  "application_id": "69f01c05-5d68-412e-9baa-07c2a5adfebc",
  "name": "Word",
  "name_e": "",
  "name_r": "",
  "description": "Microsoft Word ist eine Textverarbeitungssoftware, die von Microsoft entwickelt und veröffentlicht wurde.",
  "description_e": "",
  "description_r": "",
  "thumbnail": "assets/icons/word.svg",
  "image": "",
  "url": "https://www.microsoft.com/de-de/microsoft-365/word",
  "alternatename": "Microsoft Word",
  "alternatename_e": "",
  "alternatename_r": "",
  "keywords": "Microsoft Word, Textverarbeitung, Texteditor",
  "keywords_e": "",
  "keywords_r": "",
  "version": "Microsoft Word 2021",
  "applicationtype_id": "f08cca44-ca0f-4c50-ab5d-f58731cd5b0b"
 },
 {
  "application_id": "d9579792-b023-4afd-8eea-b22e5a91a3ec",
  "name": "Excel",
  "name_e": "",
  "name_r": "",
  "description": "Microsoft Excel ist eine Tabellenkalkulationssoftware, die von Microsoft entwickelt und veröffentlicht wurde.",
  "description_e": "",
  "description_r": "",
  "thumbnail": "assets/icons/excel.svg",
  "image": "",
  "url": "https://www.microsoft.com/de-de/microsoft-365/excel",
  "alternatename": "Microsoft Excel",
  "alternatename_e": "",
  "alternatename_r": "",
  "keywords": "Microsoft Excel, Tabellenkalkulation, Berechnung, Datenanalyse",
  "keywords_e": "",
  "keywords_r": "",
  "version": "Microsoft Excel 2021",
  "applicationtype_id": "f08cca44-ca0f-4c50-ab5d-f58731cd5b0b"
 },
 {
  "application_id": "8c9f5b2a-0385-4ded-93a4-33aa4f242b7b",
  "name": "PowerPoint",
  "name_e": "",
  "name_r": "",
  "description": "Microsoft PowerPoint ist eine Präsentationssoftware, die von Microsoft entwickelt und veröffentlicht wurde.",
  "description_e": "",
  "description_r": "",
  "thumbnail": "assets/icons/powerpoint.svg",
  "image": "",
  "url": "https://www.microsoft.com/de-de/microsoft-365/powerpoint",
  "alternatename": "Microsoft PowerPoint",
  "alternatename_e": "",
  "alternatename_r": "",
  "keywords": "Microsoft PowerPoint, Präsentation, Slideshow",
  "keywords_e": "",
  "keywords_r": "",
  "version": "Microsoft PowerPoint 2021",
  "applicationtype_id": "f08cca44-ca0f-4c50-ab5d-f58731cd5b0b"
 },
 {
  "application_id": "b44d8f76-7063-4ea8-a32d-edfc108d9c01",
  "name": "Access",
  "name_e": "",
  "name_r": "",
  "description": "Microsoft Access ist ein Datenbankmanagementsystem, das von Microsoft entwickelt und veröffentlicht wurde.",
  "description_e": "",
  "description_r": "",
  "thumbnail": "assets/icons/access.svg",
  "image": "",
  "url": "https://www.microsoft.com/de-de/microsoft-365/access",
  "alternatename": "Microsoft Access",
  "alternatename_e": "",
  "alternatename_r": "",
  "keywords": "Microsoft Access, Datenbankmanagementsystem, relationale Datenbank",
  "keywords_e": "",
  "keywords_r": "",
  "version": "Microsoft Access 2021",
  "applicationtype_id": "f08cca44-ca0f-4c50-ab5d-f58731cd5b0b"
 },
 {
  "application_id": "bad59dce-4208-494e-aa28-05d606df5e46",
  "name": "Outlook",
  "name_e": "",
  "name_r": "",
  "description": "Outlook ist ein E-Mail-Client und Personal Information Manager von Microsoft, der Teil der Microsoft Office Suite ist.",
  "description_e": "",
  "description_r": "",
  "thumbnail": "assets/icons/outlook.svg",
  "image": "",
  "url": "https://www.microsoft.com/de-de/microsoft-365/outlook",
  "alternatename": "Microsoft Outlook",
  "alternatename_e": "",
  "alternatename_r": "",
  "keywords": "Microsoft Outlook, E-Mail-Client, Personal Information Manager, Microsoft Office",
  "keywords_e": "",
  "keywords_r": "",
  "version": "Microsoft Outlook 2021",
  "applicationtype_id": "f08cca44-ca0f-4c50-ab5d-f58731cd5b0b"
 },
 {
  "application_id": "7f80f4d9-fce5-4e2c-8d46-e0aafa9492e3",
  "name": "HTML",
  "name_e": "",
  "name_r": "",
  "description": "HTML (Hypertext Markup Language) ist eine Auszeichnungssprache, die zur Erstellung der Struktur und des Inhalts von Webseiten verwendet wird.",
  "description_e": "",
  "description_r": "",
  "thumbnail": "assets/icons/html.svg",
  "image": "",
  "url": "https://developer.mozilla.org/de/docs/Web/HTML",
  "alternatename": "Hypertext Markup Language",
  "alternatename_e": "",
  "alternatename_r": "",
  "keywords": "HTML, Hypertext Markup Language, Webentwicklung",
  "keywords_e": "",
  "keywords_r": "",
  "version": "HTML5",
  "applicationtype_id": "2d68d6b3-156e-454c-902f-b53938bba5d3"
 },
 {
  "application_id": "bdd3fa72-d6fb-455a-80f8-d2ae365f9c44",
  "name": "CSS",
  "name_e": "",
  "name_r": "",
  "description": "CSS (Cascading Style Sheets) ist eine Formatierungssprache, die verwendet wird, um die Darstellung eines in HTML oder XML geschriebenen Dokuments zu beschreiben.",
  "description_e": "",
  "description_r": "",
  "thumbnail": "assets/icons/css.svg",
  "image": "",
  "url": "https://developer.mozilla.org/de/docs/Web/CSS",
  "alternatename": "Cascading Style Sheets",
  "alternatename_e": "",
  "alternatename_r": "",
  "keywords": "CSS, Cascading Style Sheets, Formatierungssprache, Webentwicklung",
  "keywords_e": "",
  "keywords_r": "",
  "version": "CSS3",
  "applicationtype_id": "2d68d6b3-156e-454c-902f-b53938bba5d3"
 },
 {
  "application_id": "7acb093e-852d-4260-97fe-eb38e2e96ba1",
  "name": "SCSS",
  "name_e": "",
  "name_r": "",
  "description": "SCSS (Sassy CSS) ist eine Vorverarbeitungsskriptsprache, die eine Erweiterung von CSS darstellt und Funktionen wie Variablen, Mixins und Verschachtelung hinzufügt.",
  "description_e": "",
  "description_r": "",
  "thumbnail": "assets/icons/scss.svg",
  "image": "",
  "url": "https://sass-lang.com/documentation",
  "alternatename": "Syntactically Awesome Style Sheets",
  "alternatename_e": "",
  "alternatename_r": "",
  "keywords": "SCSS, Sassy CSS, Formatierungssprache, Webentwicklung",
  "keywords_e": "",
  "keywords_r": "",
  "version": "SCSS",
  "applicationtype_id": "2d68d6b3-156e-454c-902f-b53938bba5d3"
 },
 {
  "application_id": "79b196b4-628d-4814-b50f-4445f3ee8ef3",
  "name": "JavaScript",
  "name_e": "",
  "name_r": "",
  "description": "JavaScript ist eine objektorientierte, höhere Programmiersprache, die verwendet wird, um interaktive Effekte in Webbrowsern zu erzeugen.",
  "description_e": "",
  "description_r": "",
  "thumbnail": "assets/icons/js.svg",
  "image": "",
  "url": "https://developer.mozilla.org/de/docs/Web/JavaScript",
  "alternatename": "JS",
  "alternatename_e": "",
  "alternatename_r": "",
  "keywords": "JavaScript, JS, Programmiersprache, Webentwicklung",
  "keywords_e": "",
  "keywords_r": "",
  "version": "ES12",
  "applicationtype_id": "2d68d6b3-156e-454c-902f-b53938bba5d3"
 },
 {
  "application_id": "df9d3b76-080c-49cc-b647-f5e0c7fd0f09",
  "name": "TypeScript",
  "name_e": "",
  "name_r": "",
  "description": "TypeScript ist ein typisierter Überbau von JavaScript, der zu normalem JavaScript kompiliert.",
  "description_e": "",
  "description_r": "",
  "thumbnail": "assets/icons/ts.svg",
  "image": "",
  "url": "https://www.typescriptlang.org/",
  "alternatename": "TS",
  "alternatename_e": "",
  "alternatename_r": "",
  "keywords": "TypeScript, TS, Programmiersprache, Webentwicklung",
  "keywords_e": "",
  "keywords_r": "",
  "version": "4.4",
  "applicationtype_id": "2d68d6b3-156e-454c-902f-b53938bba5d3"
 },
 {
  "application_id": "58751126-28ff-43e0-a932-02994d34dc00",
  "name": "PHP",
  "name_e": "",
  "name_r": "",
  "description": "PHP (Hypertext Preprocessor) ist eine serverseitige Skriptsprache, die zur Erstellung dynamischer Webseiten verwendet wird.",
  "description_e": "",
  "description_r": "",
  "thumbnail": "assets/icons/php.svg",
  "image": "",
  "url": "https://www.php.net/",
  "alternatename": "Hypertext Preprocessor",
  "alternatename_e": "",
  "alternatename_r": "",
  "keywords": "PHP, Hypertext Preprocessor, Programmiersprache, Webentwicklung",
  "keywords_e": "",
  "keywords_r": "",
  "version": "8.1",
  "applicationtype_id": "2d68d6b3-156e-454c-902f-b53938bba5d3"
 },
 {
  "application_id": "be31bdb3-d7d4-46e9-a4c6-b22785d3c420",
  "name": "Java",
  "name_e": "",
  "name_r": "",
  "description": "Java ist eine objektorientierte Programmiersprache, die darauf ausgelegt ist, so wenige Implementierungsabhängigkeiten wie möglich zu haben.",
  "description_e": "",
  "description_r": "",
  "thumbnail": "assets/icons/java.svg",
  "image": "",
  "url": "https://www.java.com/de/",
  "alternatename": "Java SE",
  "alternatename_e": "",
  "alternatename_r": "",
  "keywords": "Java, Java SE, Programmiersprache, Softwareentwicklung",
  "keywords_e": "",
  "keywords_r": "",
  "version": "17",
  "applicationtype_id": "2d68d6b3-156e-454c-902f-b53938bba5d3"
 },
 {
  "application_id": "22048a44-569e-4782-ab0d-e4b6cd5cc57c",
  "name": "Python",
  "name_e": "",
  "name_r": "",
  "description": "Python ist eine interpretierte Hochsprachen-Programmiersprache, die Code-Lesbarkeit und Benutzerfreundlichkeit betont.",
  "description_e": "",
  "description_r": "",
  "thumbnail": "assets/icons/python.svg",
  "image": "",
  "url": "https://www.python.org/",
  "alternatename": "Python 3",
  "alternatename_e": "",
  "alternatename_r": "",
  "keywords": "Python, Python 3, Programmiersprache, Softwareentwicklung",
  "keywords_e": "",
  "keywords_r": "",
  "version": "3.10",
  "applicationtype_id": "2d68d6b3-156e-454c-902f-b53938bba5d3"
 },
 {
  "application_id": "b0a1e772-c42b-4b84-b667-4a8a286f2411",
  "name": "MySQL",
  "name_e": "",
  "name_r": "",
  "description": "MySQL ist ein beliebtes, Open-Source-Relationales-Datenbankmanagementsystem.",
  "description_e": "",
  "description_r": "",
  "thumbnail": "assets/icons/mysql.svg",
  "image": "",
  "url": "https://www.mysql.com/",
  "alternatename": "Structured Query Language",
  "alternatename_e": "",
  "alternatename_r": "",
  "keywords": "MySQL, Strukturierte Abfragesprache, Datenbankmanagementsystem, Softwareentwicklung",
  "keywords_e": "",
  "keywords_r": "",
  "version": "8.0",
  "applicationtype_id": "2d68d6b3-156e-454c-902f-b53938bba5d3"
 },
 {
  "application_id": "b148bdbb-c4cb-4c07-bd35-a7298b36b3b8",
  "name": "C#",
  "name_e": "",
  "name_r": "",
  "description": "C# ist eine moderne, multiparadigmatische Programmiersprache, die von Microsoft entwickelt wurde.",
  "description_e": "",
  "description_r": "",
  "thumbnail": "assets/icons/csharp.svg",
  "image": "",
  "url": "https://docs.microsoft.com/de-de/dotnet/csharp/",
  "alternatename": "C Sharp",
  "alternatename_e": "",
  "alternatename_r": "",
  "keywords": "C#, C Sharp, Programmiersprache, Softwareentwicklung",
  "keywords_e": "",
  "keywords_r": "",
  "version": "10.0",
  "applicationtype_id": "2d68d6b3-156e-454c-902f-b53938bba5d3"
 },
 {
  "application_id": "411bdbfa-3c63-4851-a602-736e8207b05c",
  "name": "Bash",
  "name_e": "",
  "name_r": "",
  "description": "Bash ist ein Shell-Programm für Unix-ähnliche Betriebssysteme, das Benutzern ermöglicht, Befehle einzugeben, um mit dem Betriebssystem zu interagieren.",
  "description_e": "",
  "description_r": "",
  "thumbnail": "assets/icons/bash.svg",
  "image": "",
  "url": "https://www.gnu.org/software/bash/",
  "alternatename": "Bourne-Again SHell",
  "alternatename_e": "",
  "alternatename_r": "",
  "keywords": "Bash, Shell, Befehlszeilenschnittstelle, CLI, Unix-ähnlich",
  "keywords_e": "",
  "keywords_r": "",
  "version": "Bash 5.1.8",
  "applicationtype_id": "2d68d6b3-156e-454c-902f-b53938bba5d3"
 },
 {
  "application_id": "52c145ce-7304-47c0-bb1f-4e7389e4e226",
  "name": "FreeMarker",
  "name_e": "",
  "name_r": "",
  "description": "FreeMarker ist ein Template-Engine, die die Erstellung dynamischer Webseiten durch die Generierung von Textausgaben auf der Grundlage von Vorlagen ermöglicht.",
  "description_e": "",
  "description_r": "",
  "thumbnail": "assets/icons/freemarker.svg",
  "image": "",
  "url": "https://freemarker.apache.org/",
  "alternatename": "Apache FreeMarker",
  "alternatename_e": "",
  "alternatename_r": "",
  "keywords": "FreeMarker, Template Engine, Java",
  "keywords_e": "",
  "keywords_r": "",
  "version": "2.3.31",
  "applicationtype_id": "2d68d6b3-156e-454c-902f-b53938bba5d3"
 },
 {
  "application_id": "f2b2ffa7-083a-4c2b-b54b-af9b32227cd5",
  "name": "PostgreSQL",
  "name_e": "",
  "name_r": "",
  "description": "PostgreSQL ist ein leistungsstarkes Open-Source-Relationales-Datenbankmanagementsystem.",
  "description_e": "",
  "description_r": "",
  "thumbnail": "assets/icons/postgres.svg",
  "image": "",
  "url": "https://www.postgresql.org/",
  "alternatename": "Postgres",
  "alternatename_e": "",
  "alternatename_r": "",
  "keywords": "PostgreSQL, Postgres, Strukturierte Abfragesprache, Datenbankmanagementsystem, Softwareentwicklung",
  "keywords_e": "",
  "keywords_r": "",
  "version": "14.0",
  "applicationtype_id": "2d68d6b3-156e-454c-902f-b53938bba5d3"
 },
 {
  "application_id": "e6429785-c4c5-4681-aff3-f9a6a5198904",
  "name": "Ableton Live 10",
  "name_e": "",
  "name_r": "",
  "description": "Ableton Live 10 ist eine digitale Audio-Workstation für macOS und Windows. Es wird hauptsächlich zum Komponieren, Aufnehmen, Remixen und Arrangieren von Musik verwendet.",
  "description_e": "",
  "description_r": "",
  "thumbnail": "assets/icons/ableton-live.svg",
  "image": "",
  "url": "https://www.ableton.com/de/live/",
  "alternatename": "Ableton",
  "alternatename_e": "",
  "alternatename_r": "",
  "keywords": "Ableton Live 10, DAW, Musikproduktion, Audio-Workstation",
  "keywords_e": "",
  "keywords_r": "",
  "version": "10.1.30",
  "applicationtype_id": "f08cca44-ca0f-4c50-ab5d-f58731cd5b0b"
 },
 {
  "application_id": "de0dfffd-2587-4b8a-afa6-aa1c15160e04",
  "name": "FL Studio",
  "name_e": "",
  "name_r": "",
  "description": "FL Studio ist eine digitale Audio-Workstation für Windows. Es wird hauptsächlich zum Erstellen und Produzieren von Musik verwendet.",
  "description_e": "",
  "description_r": "",
  "thumbnail": "assets/icons/fl-studio.svg",
  "image": "",
  "url": "https://www.image-line.com/flstudio/",
  "alternatename": "FruityLoops",
  "alternatename_e": "",
  "alternatename_r": "",
  "keywords": "FL Studio, FruityLoops, DAW, Musikproduktion, Audio-Workstation",
  "keywords_e": "",
  "keywords_r": "",
  "version": "20.8.4",
  "applicationtype_id": "f08cca44-ca0f-4c50-ab5d-f58731cd5b0b"
 },
 {
  "application_id": "2f57ea53-0546-4c58-97a9-8186a317cea4",
  "name": "Magnolia",
  "name_e": "",
  "name_r": "",
  "description": "Magnolia ist ein Open-Source-Content-Management-System (CMS) zur Verwaltung von Inhalten auf Websites und anderen digitalen Kanälen. Es ist in Java geschrieben und wurde von Magnolia International Ltd. entwickelt.",
  "description_e": "",
  "description_r": "",
  "thumbnail": "assets/icons/magnolia.webp",
  "image": "",
  "url": "https://www.magnolia-cms.com/",
  "alternatename": "Magnolia CMS",
  "alternatename_e": "",
  "alternatename_r": "",
  "keywords": "Open-Source, Content-Management-System, Java, Magnolia International Ltd.",
  "keywords_e": "",
  "keywords_r": "",
  "version": "6.2.4",
  "applicationtype_id": "00b3119a-9a26-4776-817c-7e83a77f0913"
 },
 {
  "application_id": "d7a5763f-8676-4ef3-977c-25a416b9a841",
  "name": "JCR",
  "name_e": "",
  "name_r": "",
  "description": "Java Content Repositories (JCR) ist ein Standard des Java Community Process (JCP), der eine Schnittstelle für Content-Repositorys definiert. Ein Content-Repository ist eine Art Datenbank, in der nicht nur Daten gespeichert werden, sondern auch alle Arten von digitalen Assets, wie Bilder, Videos oder Dokumente.",
  "description_e": "",
  "description_r": "",
  "thumbnail": "assets/icons/java.svg",
  "image": "",
  "url": "https://jcp.org/en/jsr/detail?id=170",
  "alternatename": "Java Content Repositories",
  "alternatename_e": "",
  "alternatename_r": "",
  "keywords": "JCR, Java Community Process",
  "keywords_e": "",
  "keywords_r": "",
  "version": "2.0",
  "applicationtype_id": "2d68d6b3-156e-454c-902f-b53938bba5d3"
 },
 {
  "application_id": "e827957a-da65-43fb-afe7-205c23fa0ec3",
  "name": "Docker",
  "name_e": "",
  "name_r": "",
  "description": "Docker ist eine Software, die es ermöglicht, Anwendungen und ihre Abhängigkeiten in sogenannten Containern zu verpacken und bereitzustellen. Dadurch wird eine einfache und schnelle Bereitstellung von Anwendungen ermöglicht, da Container unabhängig von der zugrunde liegenden Infrastruktur ausgeführt werden können.",
  "description_e": "",
  "description_r": "",
  "thumbnail": "assets/icons/docker.svg",
  "image": "",
  "url": "https://www.docker.com/",
  "alternatename": "Docker Container",
  "alternatename_e": "",
  "alternatename_r": "",
  "keywords": "Container, Virtualisierung",
  "keywords_e": "",
  "keywords_r": "",
  "version": "20.10.7",
  "applicationtype_id": "f08cca44-ca0f-4c50-ab5d-f58731cd5b0b"
 },
 {
  "application_id": "543f4bac-d74c-4c47-8355-89b7de39e3c8",
  "name": "Schema Markup",
  "name_e": "",
  "name_r": "",
  "description": "Schema Markup ist eine Form von strukturierten Daten, die verwendet werden, um Informationen auf Webseiten zu kennzeichnen. Diese strukturierten Daten werden von Suchmaschinen genutzt, um Informationen besser zu verstehen und zu interpretieren. Dadurch können Suchergebnisse in den Suchmaschinen verbessert werden und eine bessere Sichtbarkeit in den Suchergebnissen erzielt werden.",
  "description_e": "",
  "description_r": "",
  "thumbnail": "assets/icons/schema.webp",
  "image": "",
  "url": "https://schema.org/docs/gs.html",
  "alternatename": "Structured Data",
  "alternatename_e": "",
  "alternatename_r": "",
  "keywords": "Schema.org, strukturierte Daten",
  "keywords_e": "",
  "keywords_r": "",
  "version": "4.2",
  "applicationtype_id": "b4d1e8ad-657e-4c32-8b9c-3ba8f59f74eb"
 },
 {
  "application_id": "0b0307cc-aa00-45a9-8797-079d47b94911",
  "name": "Firebase",
  "name_e": "",
  "name_r": "",
  "description": "Firebase ist eine Plattform von Google, die es Entwicklern ermöglicht, schnell und einfach mobile und Webanwendungen zu entwickeln. Firebase bietet eine Vielzahl von Diensten wie Datenbanken, Authentifizierung, Hosting und Push-Benachrichtigungen.",
  "description_e": "",
  "description_r": "",
  "thumbnail": "assets/icons/firebase.svg",
  "image": "",
  "url": "https://firebase.google.com/",
  "alternatename": "Google Firebase",
  "alternatename_e": "",
  "alternatename_r": "",
  "keywords": "Mobile App Entwicklung, Web Entwicklung",
  "keywords_e": "",
  "keywords_r": "",
  "version": "9.3.0",
  "applicationtype_id": "f08cca44-ca0f-4c50-ab5d-f58731cd5b0b"
 },
 {
  "application_id": "95bd0647-8722-4592-9b8c-539a7419a4f9",
  "name": "Blender",
  "name_e": "",
  "name_r": "",
  "description": "Blender ist eine kostenlose, Open-Source-Software zur Erstellung von 3D-Modellen, Animationen, visuellen Effekten, Kunstwerken und Videospielen. Blender wird von einer aktiven Community entwickelt und bietet eine breite Palette von Werkzeugen und Funktionen für die Erstellung von 3D-Inhalten.",
  "description_e": "",
  "description_r": "",
  "thumbnail": "assets/icons/blender.svg",
  "image": "",
  "url": "https://www.blender.org/",
  "alternatename": "Blender 3D",
  "alternatename_e": "",
  "alternatename_r": "",
  "keywords": "3D-Modellierung, Animation, visuelle Effekte",
  "keywords_e": "",
  "keywords_r": "",
  "version": "3.0",
  "applicationtype_id": "f08cca44-ca0f-4c50-ab5d-f58731cd5b0b"
 },
 {
  "application_id": "8aaff95b-22e6-4b11-9262-2ae0f0409e7b",
  "name": "Angular",
  "name_e": "",
  "name_r": "",
  "description": "Angular is a TypeScript-based open-source web application framework. It is used to build dynamic web applications that run in the browser. Angular is maintained by Google and is one of the most popular frameworks for building web applications.",
  "description_e": "",
  "description_r": "",
  "thumbnail": "assets/icons/angular.svg",
  "image": "",
  "url": "https://angular.io/",
  "alternatename": "Angular 4",
  "alternatename_e": "",
  "alternatename_r": "",
  "keywords": "Angular, TypeScript, web application framework, Google",
  "keywords_e": "",
  "keywords_r": "",
  "version": "12.2.5",
  "applicationtype_id": "b4d1e8ad-657e-4c32-8b9c-3ba8f59f74eb"
 },
 {
  "application_id": "623c0624-aba0-4a10-a879-7ffc327bdfc3",
  "name": "Regex",
  "name_e": "",
  "name_r": "",
  "description": "Regex ist eine Abkürzung für regulärer Ausdruck und bezieht sich auf Muster oder Vorlagen, die zur Suche und Manipulation von Zeichenketten in Texten verwendet werden.",
  "description_e": "",
  "description_r": "",
  "thumbnail": "assets/icons/regex.svg",
  "image": "",
  "url": "https://regex101.com/",
  "alternatename": "Regular Expression",
  "alternatename_e": "",
  "alternatename_r": "",
  "keywords": "Regex, regulärer Ausdruck, Muster, Vorlagen, Zeichenketten, Text",
  "keywords_e": "",
  "keywords_r": "",
  "version": "",
  "applicationtype_id": "f08cca44-ca0f-4c50-ab5d-f58731cd5b0b"
 },
 {
  "application_id": "24834c88-6c3c-4c58-9a8a-74d2a87a1dc8",
  "name": "GraphQL",
  "name_e": "",
  "name_r": "",
  "description": "GraphQL ist eine Abfragesprache für APIs und eine Laufzeitumgebung zum Erfüllen dieser Abfragen mit Ihren vorhandenen Daten.",
  "description_e": "",
  "description_r": "",
  "thumbnail": "assets/icons/graphql.svg",
  "image": "",
  "url": "https://graphql.org/",
  "alternatename": "Graph Query Language",
  "alternatename_e": "",
  "alternatename_r": "",
  "keywords": "API, Query",
  "keywords_e": "",
  "keywords_r": "",
  "version": "",
  "applicationtype_id": "2d68d6b3-156e-454c-902f-b53938bba5d3"
 }
]