[
 {
  "country_id": "c7f58ff3-9d96-4278-983c-90f1212fd9ec",
  "name": "Schweiz",
  "name_e": "",
  "name_r": "",
  "shortname": "CH"
 },
 {
  "country_id": "44d6d3e4-2fe1-4bf8-b75c-7af9ae31b583",
  "name": "Amerika",
  "name_e": "",
  "name_r": "",
  "shortname": "US"
 },
 {
  "country_id": "bf02069e-39c8-43a5-a3c5-efb679bd7cb0",
  "name": "Russland",
  "name_e": "",
  "name_r": "",
  "shortname": "RU"
 },
 {
  "country_id": "49e1d681-f83d-489c-9e38-f64c01f50b53",
  "name": "Frankreich",
  "name_e": "",
  "name_r": "",
  "shortname": "FR"
 }
]